mycalc/calculator.py
setuptool_test_file-0.0.1.dist-info/METADATA
setuptool_test_file-0.0.1.dist-info/WHEEL
setuptool_test_file-0.0.1.dist-info/top_level.txt
setuptool_test_file-0.0.1.dist-info/RECORD
