Metadata-Version: 2.1
Name: setuptool-test-file
Version: 0.0.1
Summary: oss-dev my calculator 0001
Home-page: https://github.com/ourwater5287/setuptools
Download-URL: https://github.com/sejin-chun/calc0001.git
Author: changuk
License: UNKNOWN
Platform: UNKNOWN
Classifier: Programming Language :: Python :: 3
